databus/__init__.py
databus/client/__init__.py
databus/client/client.py
databus/client/client_passenger.py
databus/client/external_config.py
databus/client/log.py
databus/client/user.py
databus/database/__init__.py
databus/database/abstract_database.py
databus/database/abstract_factory.py
databus/database/difference_check.py
databus/database/primal_factory.py
databus/database/export/__init__.py
databus/database/export/export.py
databus/database/export/export_package.py
databus/database/export/export_request.py
databus/database/json_db/__init__.py
databus/database/json_db/json_client.py
databus/database/json_db/json_database.py
databus/database/json_db/json_database_arguments.py
databus/database/json_db/json_log.py
databus/database/json_db/json_path_builder.py
databus/database/json_db/json_queue.py
databus/database/json_db/json_toolkit.py
databus/database/sql_db/__init__.py
databus/database/sql_db/action_decider.py
databus/database/sql_db/delete_builder.py
databus/database/sql_db/insert_builder.py
databus/database/sql_db/modifiable.py
databus/database/sql_db/path_builder.py
databus/database/sql_db/query_helper.py
databus/database/sql_db/sql_database.py
databus/database/sql_db/sql_database_arguments.py
databus/database/sql_db/table.py
databus/database/sql_db/update_builder.py
databus/database/sql_db/value_conversion.py
databus/database/sql_db/where_builder.py
databus/database/sql_db/driver/__init__.py
databus/database/sql_db/driver/abstract_driver.py
databus/database/sql_db/driver/pyodbc_driver.py
databus/dispatcher/__init__.py
databus/dispatcher/abstract_dispatcher.py
databus/dispatcher/abstract_factory.py
databus/dispatcher/observer.py
databus/dispatcher/primal_dispatcher.py
databus/dispatcher/primal_factory.py
databus/driver/__init__.py
databus/driver/abstract_driver.py
databus/driver/abstract_factory.py
databus/driver/primal_driver.py
databus/driver/primal_factory.py
databus/passenger/__init__.py
databus/passenger/abstract_factory.py
databus_keremkoseoglu-7.0.0.dist-info/LICENSE
databus_keremkoseoglu-7.0.0.dist-info/METADATA
databus_keremkoseoglu-7.0.0.dist-info/WHEEL
databus_keremkoseoglu-7.0.0.dist-info/top_level.txt
databus_keremkoseoglu-7.0.0.dist-info/RECORD
