Metadata-Version: 2.1
Name: databus-keremkoseoglu
Version: 7.0.0
Summary: Databus is a framework to transfer data between systems.
Home-page: https://github.com/keremkoseoglu/databus
Author: Kerem Koseoglu
Author-email: kerem@keremkoseoglu.com
License: UNKNOWN
Platform: UNKNOWN
Classifier: Programming Language :: Python :: 3
Classifier: License :: OSI Approved :: MIT License
Classifier: Operating System :: OS Independent
Requires-Python: >=3.6.5
Requires-Dist: cython
Requires-Dist: flask
Requires-Dist: pyodbc
Requires-Dist: urlextract
Requires-Dist: vibhaga-keremkoseoglu
Requires-Dist: waitress
